pamly-0.3.5.dist-info/METADATA
pamly-0.3.5.dist-info/WHEEL
pamly/__init__.py
pamly/pamly.cpython-311-aarch64-linux-gnu.so
pamly-0.3.5.dist-info/RECORD
