Metadata-Version: 2.3
Name: pamly
Version: 0.3.5
Classifier: Programming Language :: Rust
Classifier: Programming Language :: Python :: Implementation :: CPython
Classifier: Programming Language :: Python :: Implementation :: PyPy
Summary: Command line interface for digital pathology tools.
Keywords: pathology
Home-Page: https://github.com/spang-lab/pamly-lib
Author: Michael Huttner<michael@mhuttner.com>
Author-email: Michael Huttner <pypi@mhuttner.com>
Maintainer-email: Michael Huttner <pypi@mhuttner.com>
License: MIT
Requires-Python: >=3.8
Project-URL: Source Code, https://github.com/spang-lab/pamly-lib
